jiter/__init__.py
jiter/jiter.cpython-312.so
jiter_qpython-0.7.0.dist-info/METADATA
jiter_qpython-0.7.0.dist-info/WHEEL
jiter_qpython-0.7.0.dist-info/top_level.txt
jiter_qpython-0.7.0.dist-info/RECORD
